setup.py
svjqondor.py
svjqondor.egg-info/PKG-INFO
svjqondor.egg-info/SOURCES.txt
svjqondor.egg-info/dependency_links.txt
svjqondor.egg-info/not-zip-safe
svjqondor.egg-info/top_level.txt