Metadata-Version: 1.0
Name: svjqondor
Version: 0.3
Summary: Description text
Home-page: https://github.com/tklijnsma/svjqondor.git
Author: Thomas Klijnsma
Author-email: tklijnsm@gmail.com
License: BSD 3-Clause License
Platform: UNKNOWN
